Metadata-Version: 2.1
Name: hack4u-adraul
Version: 0.10.6
Summary: ejemplo de proyecto cursos Hack4u
Home-page: https://hack4u.io
Author: raul leon
